{
	"name": "delta_employees",
	"properties": {
		"nbformat": 4,
		"nbformat_minor": 2,
		"bigDataPool": {
			"referenceName": "aspdev01",
			"type": "BigDataPoolReference"
		},
		"sessionProperties": {
			"driverMemory": "28g",
			"driverCores": 4,
			"executorMemory": "28g",
			"executorCores": 4,
			"numExecutors": 2,
			"conf": {
				"spark.dynamicAllocation.enabled": "false",
				"spark.dynamicAllocation.minExecutors": "2",
				"spark.dynamicAllocation.maxExecutors": "2",
				"spark.autotune.trackingId": "90d17507-e34f-4178-bf3b-bc3f10acc4e0"
			}
		},
		"metadata": {
			"saveOutput": true,
			"enableDebugMode": false,
			"kernelspec": {
				"name": "synapse_pyspark",
				"display_name": "Synapse PySpark"
			},
			"language_info": {
				"name": "python"
			},
			"a365ComputeOptions": {
				"id": "/subscriptions/196bbd4f-684b-4640-a34c-9086a36e659c/resourceGroups/COVID19/providers/Microsoft.Synapse/workspaces/covid19/bigDataPools/aspdev01",
				"name": "aspdev01",
				"type": "Spark",
				"endpoint": "https://covid19.dev.azuresynapse.net/livyApi/versions/2019-11-01-preview/sparkPools/aspdev01",
				"auth": {
					"type": "AAD",
					"authResource": "https://dev.azuresynapse.net"
				},
				"sparkVersion": "3.2",
				"nodeCount": 10,
				"cores": 4,
				"memory": 28,
				"automaticScaleJobs": false
			},
			"sessionKeepAliveTimeout": 30
		},
		"cells": [
			{
				"cell_type": "code",
				"source": [
					"# Define column headers\r\n",
					"columns = [\"Employee\",\"Salary\"]\r\n",
					"\r\n",
					"# Define data for original dataframe\r\n",
					"empOriginal = [(\"Employee_1\",50000),(\"Employee_2\",55000)]\r\n",
					"\r\n",
					"# Define data for updates dataframe\r\n",
					"empUpdates = [(\"Employee_1\",50000),(\"Employee_2\",60000),(\"Employee_3\",55000)]\r\n",
					"\r\n",
					"# Create dataframe with orignial employee data\r\n",
					"dfOriginal = spark.createDataFrame(data = empOriginal,schema = columns)\r\n",
					"\r\n",
					"# Create dataframe with updated employee data\r\n",
					"dfUpdates = spark.createDataFrame(data = empUpdates,schema = columns)\r\n",
					"\r\n",
					"# Display dfOriginal\r\n",
					"dfOriginal.show()\r\n",
					"\r\n",
					"# Display dfUpdates\r\n",
					"dfUpdates.show()"
				],
				"execution_count": 1
			},
			{
				"cell_type": "code",
				"metadata": {
					"jupyter": {
						"source_hidden": false,
						"outputs_hidden": false
					},
					"nteract": {
						"transient": {
							"deleting": false
						}
					}
				},
				"source": [
					"# Create temp views of both the dfOriginal and dfUpdates dataframes \r\n",
					"# so that we can easily query them with Spark SQL later\r\n",
					"\r\n",
					"#dfOriginal\r\n",
					"dfOriginal.createOrReplaceTempView('Employee_Original')\r\n",
					"\r\n",
					"#dfUpdates\r\n",
					"dfUpdates.createOrReplaceTempView('Employee_Updates')"
				],
				"execution_count": 2
			},
			{
				"cell_type": "code",
				"metadata": {
					"jupyter": {
						"source_hidden": false,
						"outputs_hidden": false
					},
					"nteract": {
						"transient": {
							"deleting": false
						}
					},
					"microsoft": {
						"language": "sparksql"
					},
					"collapsed": false
				},
				"source": [
					"%%sql\r\n",
					"-- Create Delta Lake table, define schema and location\r\n",
					"CREATE TABLE DELTA_Employees (\r\n",
					"  Employee STRING NOT NULL,\r\n",
					"  Salary INT NOT NULL,\r\n",
					"  BeginDate DATE NOT NULL,\r\n",
					"  EndDate DATE NOT NULL,\r\n",
					"  CurrentRecord INT NOT NULL \r\n",
					")\r\n",
					"USING DELTA\r\n",
					"-- specify data lake folder location\r\n",
					"LOCATION '/Delta_Data/Employees/' "
				],
				"execution_count": 3
			},
			{
				"cell_type": "code",
				"metadata": {
					"jupyter": {
						"source_hidden": false,
						"outputs_hidden": false
					},
					"nteract": {
						"transient": {
							"deleting": false
						}
					},
					"microsoft": {
						"language": "sparksql"
					},
					"collapsed": false
				},
				"source": [
					"%%sql\r\n",
					"-- Merge statement to handle upsert of dfOrginal dataset into DELTA_Employees table\r\n",
					"MERGE INTO delta_employees t\r\n",
					"USING (\r\n",
					"    SELECT emp.Employee AS MergeKey, emp.*\r\n",
					"    FROM Employee_Original AS emp\r\n",
					"\r\n",
					"    UNION ALL\r\n",
					"\r\n",
					"    SELECT NULL AS MergeKey, emp.*\r\n",
					"    FROM Employee_Original AS emp\r\n",
					"    JOIN delta_employees AS de ON emp.Employee = de.Employee\r\n",
					"    WHERE de.CurrentRecord = 1 AND emp.Salary <> de.Salary\r\n",
					") s\r\n",
					"ON t.Employee = s.MergeKey\r\n",
					"WHEN MATCHED AND t.CurrentRecord = 1 AND t.Salary <> s.Salary THEN\r\n",
					"  UPDATE SET t.CurrentRecord = 0, t.EndDate = (CURRENT_DATE)\r\n",
					"WHEN NOT MATCHED THEN\r\n",
					"  INSERT (Employee, Salary, BeginDate, EndDate, CurrentRecord) VALUES (s.Employee, s.Salary, CURRENT_DATE, '2999-12-31',1)"
				],
				"execution_count": 4
			},
			{
				"cell_type": "code",
				"metadata": {
					"jupyter": {
						"source_hidden": false,
						"outputs_hidden": false
					},
					"nteract": {
						"transient": {
							"deleting": false
						}
					},
					"microsoft": {
						"language": "sparksql"
					},
					"collapsed": false
				},
				"source": [
					"%%sql\r\n",
					"SELECT *\r\n",
					"FROM DELTA_Employees\r\n",
					"ORDER BY Employee"
				],
				"execution_count": 5
			},
			{
				"cell_type": "code",
				"metadata": {
					"jupyter": {
						"source_hidden": false,
						"outputs_hidden": false
					},
					"nteract": {
						"transient": {
							"deleting": false
						}
					},
					"microsoft": {
						"language": "sparksql"
					},
					"collapsed": false
				},
				"source": [
					"%%sql\r\n",
					"-- Merge statement to handle upsert of dfUpdates into DELTA_Employees table\r\n",
					"MERGE INTO delta_employees t\r\n",
					"USING (\r\n",
					"    SELECT emp.Employee AS MergeKey, emp.*\r\n",
					"    FROM Employee_Updates AS emp\r\n",
					"\r\n",
					"    UNION ALL\r\n",
					"\r\n",
					"    SELECT NULL AS MergeKey, emp.*\r\n",
					"    FROM Employee_Updates AS emp\r\n",
					"    JOIN delta_employees AS de ON emp.Employee = de.Employee\r\n",
					"    WHERE de.CurrentRecord = 1 AND emp.Salary <> de.Salary\r\n",
					") s\r\n",
					"ON t.Employee = s.MergeKey\r\n",
					"WHEN MATCHED AND t.CurrentRecord = 1 AND t.Salary <> s.Salary THEN\r\n",
					"  UPDATE SET t.CurrentRecord = 0, t.EndDate = (CURRENT_DATE)\r\n",
					"WHEN NOT MATCHED THEN\r\n",
					"  INSERT (Employee, Salary, BeginDate, EndDate, CurrentRecord) VALUES (s.Employee, s.Salary, CURRENT_DATE, '2999-12-31',1)"
				],
				"execution_count": 6
			},
			{
				"cell_type": "code",
				"metadata": {
					"jupyter": {
						"source_hidden": false,
						"outputs_hidden": false
					},
					"nteract": {
						"transient": {
							"deleting": false
						}
					},
					"microsoft": {
						"language": "sparksql"
					},
					"collapsed": false
				},
				"source": [
					"%%sql\r\n",
					"SELECT *\r\n",
					"FROM DELTA_Employees\r\n",
					"ORDER BY Employee"
				],
				"execution_count": 7
			},
			{
				"cell_type": "code",
				"metadata": {
					"jupyter": {
						"source_hidden": false,
						"outputs_hidden": false
					},
					"nteract": {
						"transient": {
							"deleting": false
						}
					},
					"microsoft": {
						"language": "sparksql"
					},
					"collapsed": false
				},
				"source": [
					"%%sql\r\n",
					"-- Retrieve the version/change history of the Delta table\r\n",
					"DESCRIBE HISTORY default.DELTA_Employees"
				],
				"execution_count": 8
			},
			{
				"cell_type": "code",
				"metadata": {
					"jupyter": {
						"source_hidden": false,
						"outputs_hidden": false
					},
					"nteract": {
						"transient": {
							"deleting": false
						}
					}
				},
				"source": [
					"\r\n",
					"df = spark.read.format(\"delta\").option(\"versionAsOf\", 1).load(\"/Delta_Data/Employees/\")\r\n",
					"df.show()"
				],
				"execution_count": 15
			},
			{
				"cell_type": "code",
				"metadata": {
					"jupyter": {
						"source_hidden": false,
						"outputs_hidden": false
					},
					"nteract": {
						"transient": {
							"deleting": false
						}
					}
				},
				"source": [
					""
				],
				"execution_count": null
			}
		]
	}
}